vecx_langchain/__init__.py
vecx_langchain/base.py
vecx_langchain-0.1.3.dist-info/METADATA
vecx_langchain-0.1.3.dist-info/WHEEL
vecx_langchain-0.1.3.dist-info/top_level.txt
vecx_langchain-0.1.3.dist-info/RECORD
