Metadata-Version: 2.1
Name: vecx-langchain
Version: 0.1.3
Summary: Encrypted Vector Database for Secure and Fast ANN Searches with LangChain
Home-page: https://vectorxdb.ai
Author: LaunchX Labs
Author-email: vineet@launchxlabs.ai
Classifier: Programming Language :: Python :: 3
Classifier: License :: OSI Approved :: MIT License
Classifier: Operating System :: OS Independent
Requires-Python: >=3.6
Requires-Dist: langchain>=0.3.25
Requires-Dist: langchain-core>=0.3.59
Requires-Dist: vecx>=0.32.1
Requires-Dist: numpy
